odoo/addons/account_asset_from_expense/README.rst
odoo/addons/account_asset_from_expense/__init__.py
odoo/addons/account_asset_from_expense/__manifest__.py
odoo/addons/account_asset_from_expense/i18n/account_asset_from_expense.pot
odoo/addons/account_asset_from_expense/i18n/es.po
odoo/addons/account_asset_from_expense/i18n/it.po
odoo/addons/account_asset_from_expense/models/__init__.py
odoo/addons/account_asset_from_expense/models/hr_expense.py
odoo/addons/account_asset_from_expense/readme/CONTRIBUTORS.rst
odoo/addons/account_asset_from_expense/readme/DESCRIPTION.rst
odoo/addons/account_asset_from_expense/security/ir.model.access.csv
odoo/addons/account_asset_from_expense/static/description/icon.png
odoo/addons/account_asset_from_expense/static/description/index.html
odoo/addons/account_asset_from_expense/tests/__init__.py
odoo/addons/account_asset_from_expense/tests/test_account_asset_from_expense.py
odoo/addons/account_asset_from_expense/views/hr_expense_views.xml
odoo14_addon_account_asset_from_expense-14.0.1.0.1.dev8.dist-info/METADATA
odoo14_addon_account_asset_from_expense-14.0.1.0.1.dev8.dist-info/WHEEL
odoo14_addon_account_asset_from_expense-14.0.1.0.1.dev8.dist-info/top_level.txt
odoo14_addon_account_asset_from_expense-14.0.1.0.1.dev8.dist-info/RECORD
